peyes/__init__.py
peyes/_DataModels/DatasetLoader.py
peyes/_DataModels/Detector.py
peyes/_DataModels/Event.py
peyes/_DataModels/EventLabelEnum.py
peyes/_DataModels/EventMatcher.py
peyes/_DataModels/UnparsedEventLabel.py
peyes/_DataModels/config.py
peyes/_base/create.py
peyes/_base/match.py
peyes/_base/parse.py
peyes/_base/postprocess_events.py
peyes/_base/set_config.py
peyes/_utils/constants.py
peyes/_utils/event_utils.py
peyes/_utils/metric_utils.py
peyes/_utils/pixel_utils.py
peyes/_utils/vector_utils.py
peyes/_utils/visualization_utils.py
peyes/alignment_metrics/__init__.py
peyes/alignment_metrics/_signal_detection_metrics.py
peyes/alignment_metrics/_timing_differences.py
peyes/datasets/__init__.py
peyes/datasets/get_metadata.py
peyes/datasets/load_dataset.py
peyes/event_metrics/__init__.py
peyes/event_metrics/_get_features.py
peyes/event_metrics/_rates_and_transitions.py
peyes/match_metrics/__init__.py
peyes/match_metrics/_get_features.py
peyes/match_metrics/_match_evaluation.py
peyes/sample_metrics/__init__.py
peyes/sample_metrics/_calculate_metrics.py
peyes/sample_metrics/_counts_and_matrices.py
peyes/visualize/__init__.py
peyes/visualize/_event_summary.py
peyes/visualize/_features.py
peyes/visualize/_gaze.py
peyes/visualize/_scarfplot.py
peyes/visualize/_video.py
peyes-0.0.9.6.dist-info/METADATA
peyes-0.0.9.6.dist-info/WHEEL
peyes-0.0.9.6.dist-info/RECORD
