Metadata-Version: 2.4
Name: peyes
Version: 0.0.9.6
Summary: A package for eye tracking data analysis and visualization
Project-URL: Homepage, https://github.com/huji-hcnl/pEYES
Project-URL: Bug Tracker, https://github.com/huji-hcnl/pEYES/issues
Author-email: "Human Cognitive Neuroscience Lab @ HUJI" <hcnl@mail.huji.ac.il>, Jonathan Nir <jonathan.nir@mail.huji.ac.il>
Classifier: License :: OSI Approved :: MIT License
Classifier: Programming Language :: Python :: 3
Requires-Dist: kaleido==0.1.0post1
Requires-Dist: liac-arff~=2.4
Requires-Dist: numpy~=1.2
Requires-Dist: opencv-python~=4.1
Requires-Dist: overrides~=7.7
Requires-Dist: pandas~=2.2
Requires-Dist: plotly~=5.2
Requires-Dist: python-levenshtein~=0.2
Requires-Dist: remodnav~=1.1
Requires-Dist: requests~=2.32
Requires-Dist: scikit-learn~=1.5
Requires-Dist: scikit-posthocs~=0.9
Requires-Dist: scipy~=1.1
Requires-Dist: statsmodels~=0.1
Requires-Dist: tqdm~=4.6
